{
  "country_code": "BGD",
  "country_name": "Bangladesh",
  "tier": 2,
  "region": "south_asia",
  "last_updated": "2026-03-02T12:00:00Z",
  "run_id": "2026-W09",
  "macroeconomic": {
    "gdp_nominal_usd": {
      "value": 475011000000.0,
      "confidence": 0.85,
      "last_updated": "2026-03-02T00:00:00Z",
      "source": "agent_pipeline",
      "run_id": "2026-W09"
    },
    "gdp_real_growth_pct": {
      "value": 3.8,
      "confidence": 0.85,
      "last_updated": "2026-03-02T00:00:00Z",
      "source": "agent_pipeline",
      "run_id": "2026-W09"
    },
    "gdp_per_capita_usd": {
      "value": 2734.098,
      "confidence": 0.85,
      "last_updated": "2026-03-02T00:00:00Z",
      "source": "agent_pipeline",
      "run_id": "2026-W09"
    },
    "inflation_cpi_pct": {
      "value": 10,
      "confidence": 0.85,
      "last_updated": "2026-03-02T00:00:00Z",
      "source": "agent_pipeline",
      "run_id": "2026-W09"
    },
    "unemployment_rate_pct": {
      "value": 3.778,
      "confidence": 0.9,
      "last_updated": "2026-03-02T00:00:00Z",
      "source": "agent_pipeline",
      "run_id": "2026-W09"
    },
    "current_account_pct_gdp": {
      "value": 0,
      "confidence": 0.85,
      "last_updated": "2026-03-02T00:00:00Z",
      "source": "agent_pipeline",
      "run_id": "2026-W09"
    },
    "fx_reserves_usd": {
      "value": 21394795733.0405,
      "confidence": 0.9,
      "last_updated": "2026-03-02T00:00:00Z",
      "source": "agent_pipeline",
      "run_id": "2026-W09"
    },
    "govt_debt_pct_gdp": {
      "value": 40.3,
      "confidence": 0.85,
      "last_updated": "2026-03-02T00:00:00Z",
      "source": "agent_pipeline",
      "run_id": "2026-W09"
    },
    "gdp_growth_forecast_2026_pct": {
      "value": 4.9,
      "confidence": 0.85,
      "last_updated": "2026-03-02T00:00:00Z",
      "source": "agent_pipeline",
      "run_id": "2026-W09"
    },
    "sovereign_credit_rating": {
      "value": "S&P: B+, Moody's: B2, Fitch: B+",
      "confidence": 0.9,
      "last_updated": "2026-03-02T00:00:00Z",
      "source": "agent_pipeline",
      "run_id": "2026-W09"
    }
  },
  "demographic": {
    "population_total": {
      "value": 173562364,
      "confidence": 0.9,
      "last_updated": "2026-03-02T00:00:00Z",
      "source": "agent_pipeline",
      "run_id": "2026-W09"
    },
    "population_growth_pct": {
      "value": 1.21462115417186,
      "confidence": 0.9,
      "last_updated": "2026-03-02T00:00:00Z",
      "source": "agent_pipeline",
      "run_id": "2026-W09"
    },
    "life_expectancy": {
      "value": 74.672,
      "confidence": 0.85,
      "last_updated": "2026-03-02T00:00:00Z",
      "source": "agent_pipeline",
      "run_id": "2026-W09"
    }
  },
  "political": {},
  "military": {},
  "trade": {},
  "derived": {
    "resource_self_sufficiency_index": {
      "value": 0.55,
      "confidence": 0.6,
      "last_updated": "2026-03-02T12:00:00Z",
      "source": "agent_11_derived",
      "run_id": "2026-W09",
      "methodology": "Average of min(production/consumption, 1.0) for energy, food, water, minerals"
    },
    "energy_independence_index": {
      "value": 0.4,
      "confidence": 0.65,
      "last_updated": "2026-03-02T12:00:00Z",
      "source": "agent_11_derived",
      "run_id": "2026-W09",
      "methodology": "domestic_energy_production / domestic_energy_consumption, capped at 1.0"
    },
    "supply_chain_chokepoint_exposure": {
      "value": 0.37,
      "confidence": 0.6,
      "last_updated": "2026-03-02T12:00:00Z",
      "source": "agent_11_derived",
      "run_id": "2026-W09",
      "methodology": "0.6 * maritime_chokepoint_dependency + 0.4 * normalized_trade_openness"
    },
    "composite_national_power_index": {
      "value": 21.8,
      "confidence": 0.7,
      "last_updated": "2026-03-02T12:00:00Z",
      "source": "agent_11_derived",
      "run_id": "2026-W09",
      "methodology": "0.35*economic + 0.25*military + 0.20*technology + 0.10*diplomatic + 0.10*soft_power, normalized 0-100"
    },
    "political_risk_premium_bps": {
      "value": 700,
      "confidence": 0.7,
      "last_updated": "2026-03-02T12:00:00Z",
      "source": "agent_11_derived",
      "run_id": "2026-W09",
      "methodology": "Sovereign rating implied spread + adjustments for instability, conflict, sanctions, autocracy"
    },
    "market_accessibility_score": {
      "value": 0.244,
      "confidence": 0.6,
      "last_updated": "2026-03-02T12:00:00Z",
      "source": "agent_11_derived",
      "run_id": "2026-W09",
      "methodology": "Average of capital_account_openness, stock_market_cap/200, financial_dev_index, ease_of_business/100"
    }
  },
  "metadata": {
    "active_flags": [],
    "update_count": 13,
    "first_loaded": "2026-03-02T00:00:00Z",
    "data_quality": "HIGH"
  },
  "narrative": {
    "ai_generated": true,
    "generated_at": "2026-03-02T13:00:00Z",
    "run_id": "2026-W09",
    "executive_summary": "Bangladesh's BNP won a landslide election on Feb 12, providing a new government mandate. A US-Bangladesh trade deal is in progress. GDP growth at 3.8% with 10% inflation. Oil price surge creates import cost pressure. Political stability improving under new government.",
    "key_changes_this_week": [
      "BNP landslide election (Feb 12) provides new government mandate",
      "US-Bangladesh trade deal negotiations in progress",
      "Oil price surge adds inflation pressure"
    ],
    "outlook": "Bangladesh's new government has a mandate for economic reform and trade integration. Garment export sector remains the key driver. Oil import costs are a near-term headwind.",
    "investor_implications": "Bangladesh frontier market access limited. Garment sector benefits from China+1 sourcing. Taka under moderate pressure from oil costs. New government provides reform optionality.",
    "data_quality_note": "Bangladesh macro data is of medium quality. Election results confirmed."
  },
  "code": "BGD",
  "name": "Bangladesh",
  "executive_summary": "Bangladesh's BNP won a landslide election on Feb 12, providing a new government mandate. A US-Bangladesh trade deal is in progress. GDP growth at 3.8% with 10% inflation. Oil price surge creates import cost pressure. Political stability improving under new government.",
  "key_changes": [
    "BNP landslide election (Feb 12) provides new government mandate",
    "US-Bangladesh trade deal negotiations in progress",
    "Oil price surge adds inflation pressure"
  ],
  "outlook": "Bangladesh's new government has a mandate for economic reform and trade integration. Garment export sector remains the key driver. Oil import costs are a near-term headwind.",
  "investor_implications": "Bangladesh frontier market access limited. Garment sector benefits from China+1 sourcing. Taka under moderate pressure from oil costs. New government provides reform optionality.",
  "active_alerts": [
    {
      "severity": "watch",
      "title": "Bangladesh BNP wins landslide in first election since 2024 uprising; policy shift expected",
      "description": "Bangladesh held its first post-Hasina election on Feb 12 with BNP winning a landslide (209 seats). Major democratic transition after 2024 uprising. Business leaders expressed optimism but sustained confidence depends on governance quality. Energy independence at 0.4 means oil surge exposure."
    }
  ],
  "layers": {
    "endowments": {
      "population": 173562364,
      "population_growth_pct": 1.21462115417186,
      "life_expectancy": 74.672
    },
    "institutions": {
      "political_stability": {}
    },
    "economy": {
      "gdp_nominal_usd": 475011000000.0,
      "gdp_real_growth_pct": 3.8,
      "gdp_per_capita_usd": 2734.098,
      "inflation_cpi_pct": 10,
      "unemployment_rate_pct": 3.778,
      "current_account_pct_gdp": 0,
      "govt_debt_pct_gdp": 40.3,
      "fx_reserves_usd": 21394795733.0405,
      "sovereign_credit_rating": "S&P: B+, Moody's: B2, Fitch: B+",
      "central_bank_policy_rate_pct": null
    },
    "military": {},
    "relations": {},
    "derived": {
      "resource_self_sufficiency_index": 0.55,
      "energy_independence_index": 0.4,
      "supply_chain_chokepoint_exposure": 0.37,
      "composite_national_power_index": 21.8,
      "political_risk_premium_bps": 700,
      "market_accessibility_score": 0.244
    }
  }
}