{
  "country_code": "ITA",
  "country_name": "Italy",
  "tier": 1,
  "region": "europe",
  "last_updated": "2026-03-10T00:00:00Z",
  "run_id": "2026-W11",
  "macroeconomic": {
    "gdp_nominal_usd": {
      "value": 2380825077243.59,
      "confidence": 0.95,
      "last_updated": "2026-03-10T00:00:00Z",
      "source": "agent_pipeline",
      "run_id": "2026-W11"
    },
    "gdp_real_growth_pct": {
      "value": 0.692676948440536,
      "confidence": 0.95,
      "last_updated": "2026-03-10T00:00:00Z",
      "source": "agent_pipeline",
      "run_id": "2026-W11",
      "trend": "decrease",
      "trend_confidence": 0.78,
      "trend_reasoning": "Italy facing GDP headwinds from oil shock ($116/bbl Brent) and European market crash (~6% drops across indices). Energy costs rising sharply.",
      "trend_updated": "2026-03-10T12:00:00Z"
    },
    "gdp_per_capita_usd": {
      "value": 40385.3413957669,
      "confidence": 0.95,
      "last_updated": "2026-03-10T00:00:00Z",
      "source": "agent_pipeline",
      "run_id": "2026-W11"
    },
    "inflation_cpi_pct": {
      "value": 0.982373023061417,
      "confidence": 0.95,
      "last_updated": "2026-03-10T00:00:00Z",
      "source": "agent_pipeline",
      "run_id": "2026-W11",
      "trend": "growth",
      "trend_confidence": 0.78,
      "trend_reasoning": "Italy facing inflation uptick from oil shock feeding through energy, transport, and goods prices. EU admitted 'nuclear blunder' on energy policy. ECB faces stagflation dilemma ahead of March policy meeting.",
      "trend_updated": "2026-03-10T12:00:00Z"
    },
    "unemployment_rate_pct": {
      "value": 6.391,
      "confidence": 0.95,
      "last_updated": "2026-03-10T00:00:00Z",
      "source": "agent_pipeline",
      "run_id": "2026-W11"
    },
    "current_account_pct_gdp": {
      "value": 1.08253400174467,
      "confidence": 0.95,
      "last_updated": "2026-03-10T00:00:00Z",
      "source": "agent_pipeline",
      "run_id": "2026-W11",
      "trend": "decrease",
      "trend_confidence": 0.65,
      "trend_reasoning": "Italy current account deteriorating from higher oil import costs at $116/bbl.",
      "trend_updated": "2026-03-10T12:00:00Z"
    },
    "fx_reserves_usd": {
      "value": 290547246726.359,
      "confidence": 0.95,
      "last_updated": "2026-03-10T00:00:00Z",
      "source": "agent_pipeline",
      "run_id": "2026-W11"
    },
    "govt_debt_pct_gdp": {
      "value": 136.8,
      "confidence": 0.85,
      "last_updated": "2026-03-10T00:00:00Z",
      "source": "agent_pipeline",
      "run_id": "2026-W11",
      "trend": "growth",
      "trend_confidence": 0.68,
      "trend_reasoning": "Italy debt ratio rising modestly as oil shock reduces growth and increases government energy costs/subsidies. Interest rates remain elevated.",
      "trend_updated": "2026-03-10T12:00:00Z"
    },
    "gdp_growth_forecast_2026_pct": {
      "value": 0.8,
      "confidence": 0.85,
      "last_updated": "2026-03-02T12:05:00Z",
      "source": "agent_pipeline",
      "run_id": "2026-W10"
    },
    "sovereign_credit_rating": {
      "value": "S&P: BBB+, Moody's: Baa2, Fitch: BBB",
      "confidence": 0.9,
      "last_updated": "2026-03-02T12:05:00Z",
      "source": "agent_pipeline",
      "run_id": "2026-W10"
    },
    "central_bank_policy_rate_pct": {
      "value": 2.0,
      "confidence": 0.99,
      "last_updated": "2026-03-03T22:30:00Z",
      "source": "agent_pipeline",
      "run_id": "2026-W10b"
    },
    "exchange_rate_vs_usd": {
      "value": 0.8633,
      "confidence": 0.95,
      "last_updated": "2026-03-10T00:00:00Z",
      "source": "agent_pipeline",
      "run_id": "2026-W11",
      "trend": "decrease",
      "trend_confidence": 0.68,
      "trend_reasoning": "EUR under mild pressure from European market crash and energy import costs. USD safe-haven demand dominant. ECB policy response key variable.",
      "trend_updated": "2026-03-10T12:00:00Z"
    },
    "sovereign_bond_yield_10yr_pct": {
      "value": 3.51,
      "confidence": 0.55,
      "last_updated": "2026-03-10T00:00:00Z",
      "source": "agent_pipeline",
      "run_id": "2026-W11"
    },
    "total_exports_usd": {
      "value": 773888180686.25,
      "confidence": 0.95,
      "last_updated": "2026-03-10T00:00:00Z",
      "source": "agent_pipeline",
      "run_id": "2026-W11"
    },
    "total_imports_usd": {
      "value": 721835854515.781,
      "confidence": 0.95,
      "last_updated": "2026-03-10T00:00:00Z",
      "source": "agent_pipeline",
      "run_id": "2026-W11"
    },
    "inflation_forecast_2026_pct": {
      "value": 2,
      "confidence": 0.8,
      "last_updated": "2026-03-02T12:05:00Z",
      "source": "agent_pipeline",
      "run_id": "2026-W10"
    },
    "fdi_inflows_usd": {
      "value": 26903748175.4513,
      "confidence": 0.95,
      "last_updated": "2026-03-10T00:00:00Z",
      "source": "agent_pipeline",
      "run_id": "2026-W11",
      "trend": "stable",
      "trend_confidence": 0.58,
      "trend_reasoning": "Italy FDI broadly stable with mild downward pressure from global uncertainty. Gulf conflict creating risk-off sentiment across emerging markets.",
      "trend_updated": "2026-03-10T12:00:00Z"
    },
    "gdp_ppp_usd": {
      "value": 3655908756610.36,
      "confidence": 0.95,
      "last_updated": "2026-03-10T00:00:00Z",
      "source": "agent_pipeline",
      "run_id": "2026-W11"
    },
    "gini_coefficient": {
      "value": 34.3,
      "confidence": 0.95,
      "last_updated": "2026-03-10T00:00:00Z",
      "source": "agent_pipeline",
      "run_id": "2026-W11"
    },
    "fiscal_balance_pct_gdp": {
      "value": -3.3,
      "confidence": 0.85,
      "last_updated": "2026-03-10T00:00:00Z",
      "source": "agent_pipeline",
      "run_id": "2026-W11"
    }
  },
  "demographic": {
    "population_total": {
      "value": 58952704,
      "confidence": 0.95,
      "last_updated": "2026-03-10T00:00:00Z",
      "source": "agent_pipeline",
      "run_id": "2026-W11"
    },
    "population_growth_pct": {
      "value": -0.0534387378437725,
      "confidence": 0.95,
      "last_updated": "2026-03-10T00:00:00Z",
      "source": "agent_pipeline",
      "run_id": "2026-W11"
    },
    "life_expectancy": {
      "value": 83.7,
      "confidence": 0.95,
      "last_updated": "2026-03-10T00:00:00Z",
      "source": "agent_pipeline",
      "run_id": "2026-W11"
    },
    "hdi": {
      "value": 0.915,
      "confidence": 0.95,
      "last_updated": "2026-03-02T12:05:00Z",
      "source": "agent_pipeline",
      "run_id": "2026-W10"
    },
    "median_age": {
      "value": 48.4,
      "confidence": 0.85,
      "last_updated": "2026-03-02T12:05:00Z",
      "source": "agent_pipeline",
      "run_id": "2026-W10"
    },
    "labor_force_participation_pct": {
      "value": 49.302,
      "confidence": 0.95,
      "last_updated": "2026-03-10T00:00:00Z",
      "source": "agent_pipeline",
      "run_id": "2026-W11"
    },
    "health_expenditure_pct_gdp": {
      "value": 8.44437313,
      "confidence": 0.95,
      "last_updated": "2026-03-10T00:00:00Z",
      "source": "agent_pipeline",
      "run_id": "2026-W11"
    },
    "urban_population_pct": {
      "value": 69.6047535143071,
      "confidence": 0.95,
      "last_updated": "2026-03-10T00:00:00Z",
      "source": "agent_pipeline",
      "run_id": "2026-W11"
    }
  },
  "political": {},
  "military": {
    "military_spending_usd": {
      "value": 32000000000,
      "confidence": 0.7,
      "last_updated": "2026-03-02T00:00:00Z",
      "source": "SIPRI/estimates",
      "run_id": "2026-W09"
    },
    "military_expenditure_usd": {
      "value": 37400000000,
      "confidence": 0.88,
      "last_updated": "2026-03-02T12:05:00Z",
      "source": "agent_pipeline",
      "run_id": "2026-W10"
    },
    "military_expenditure_pct_gdp": {
      "value": 1.6,
      "confidence": 0.82,
      "last_updated": "2026-03-02T12:05:00Z",
      "source": "agent_pipeline",
      "run_id": "2026-W10",
      "trend": "growth",
      "trend_confidence": 0.82,
      "trend_reasoning": "Italy defense spending growing under NATO 2% commitment. SIPRI: European arms imports up 210%. All 32 NATO members now at 2% GDP target. US arms exports up 27% \u2014 Europe now top recipient region.",
      "trend_updated": "2026-03-10T12:00:00Z"
    },
    "active_military_personnel": {
      "value": 165500,
      "confidence": 0.9,
      "last_updated": "2026-03-02T12:05:00Z",
      "source": "agent_pipeline",
      "run_id": "2026-W10"
    },
    "army": {
      "main_battle_tanks": {
        "value": 203,
        "confidence": 0.85,
        "last_updated": "2026-03-02T12:05:00Z",
        "source": "agent_pipeline",
        "run_id": "2026-W10"
      }
    },
    "air_force": {
      "total_aircraft": {
        "value": 714,
        "confidence": 0.85,
        "last_updated": "2026-03-02T12:05:00Z",
        "source": "agent_pipeline",
        "run_id": "2026-W10"
      }
    },
    "navy": {
      "submarines_total": {
        "value": 8,
        "confidence": 0.88,
        "last_updated": "2026-03-02T12:05:00Z",
        "source": "agent_pipeline",
        "run_id": "2026-W10"
      }
    },
    "alliance_memberships": {
      "value": [
        "NATO",
        "EU CSDP"
      ],
      "confidence": 0.98,
      "last_updated": "2026-03-02T12:05:00Z",
      "source": "agent_pipeline",
      "run_id": "2026-W10"
    },
    "nuclear": {
      "status": {
        "value": "nuclear_sharing",
        "confidence": 0.95,
        "last_updated": "2026-03-02T12:05:00Z",
        "source": "agent_pipeline",
        "run_id": "2026-W10"
      }
    },
    "arms_exports_global_share": {
      "value": {
        "share_pct_approx": 4.5,
        "period": "2021-2025",
        "volume_change": "+157%",
        "note": "Massive increase in Italian arms exports."
      },
      "confidence": 0.85,
      "last_updated": "2026-03-10T00:00:00Z",
      "source": "agent_pipeline",
      "run_id": "2026-W11"
    }
  },
  "trade": {},
  "derived": {
    "resource_self_sufficiency_index": {
      "value": 0.3,
      "confidence": 0.7,
      "last_updated": "2026-03-10T16:00:00Z",
      "source": "agent_11_derived",
      "run_id": "2026-W11",
      "methodology": "Average of min(production/consumption, 1.0) for energy, food, water, minerals"
    },
    "energy_independence_index": {
      "value": 0.2,
      "confidence": 0.7,
      "last_updated": "2026-03-10T16:00:00Z",
      "source": "agent_11_derived",
      "run_id": "2026-W11",
      "methodology": "domestic_energy_production / domestic_energy_consumption, capped at 1.0"
    },
    "supply_chain_chokepoint_exposure": {
      "value": 0.306,
      "confidence": 0.7,
      "last_updated": "2026-03-10T16:00:00Z",
      "source": "agent_11_derived",
      "run_id": "2026-W11",
      "methodology": "0.6 * maritime_chokepoint_dependency + 0.4 * normalized_trade_openness; elevated due to active Hormuz/Suez disruption"
    },
    "composite_national_power_index": {
      "value": 54.8,
      "confidence": 0.7,
      "last_updated": "2026-03-10T16:00:00Z",
      "source": "agent_11_derived",
      "run_id": "2026-W11",
      "methodology": "0.35*economic + 0.25*military + 0.20*technology + 0.10*diplomatic + 0.10*soft_power, normalized 0-100",
      "previous_value": 48.7
    },
    "political_risk_premium_bps": {
      "value": 110,
      "confidence": 0.75,
      "last_updated": "2026-03-10T16:00:00Z",
      "source": "agent_11_derived",
      "run_id": "2026-W11",
      "methodology": "Sovereign rating implied spread + adjustments for instability, conflict, sanctions, autocracy"
    },
    "market_accessibility_score": {
      "value": 0.78,
      "confidence": 0.7,
      "last_updated": "2026-03-10T16:00:00Z",
      "source": "agent_11_derived",
      "run_id": "2026-W11",
      "methodology": "Average of capital_account_openness, stock_market_cap/200, financial_dev_index, ease_of_business/100"
    },
    "overall_investment_risk_score": {
      "value": 0.175,
      "confidence": 0.7,
      "last_updated": "2026-03-10T16:00:00Z",
      "source": "agent_11_derived",
      "run_id": "2026-W11",
      "methodology": "0.30*political_risk + 0.30*economic_risk + 0.20*financial_market_risk + 0.20*security_risk",
      "trend": "decrease",
      "trend_confidence": 0.72,
      "trend_reasoning": "Italy investment risk modestly elevated from European market crash, oil shock, and defense spending reallocation. But institutional strength provides resilience.",
      "trend_updated": "2026-03-10T12:00:00Z"
    },
    "trade_openness_trend": {
      "value": "stable",
      "confidence": 0.6,
      "reasoning": "Italy trade openness broadly stable. Global trade disruption from Hormuz primarily affects Gulf-dependent routes. Some trade rerouting benefits alternative routes.",
      "last_updated": "2026-03-10T12:00:00Z",
      "source": "agent_10_trend_estimator",
      "run_id": "2026-W11"
    },
    "top_partner_relationship_health": {
      "value": "stable",
      "confidence": 0.55,
      "reasoning": "Italy key bilateral relationships broadly unchanged this week. Global focus on Gulf conflict reduces attention on other bilateral dynamics.",
      "last_updated": "2026-03-10T12:00:00Z",
      "source": "agent_10_trend_estimator",
      "run_id": "2026-W11"
    },
    "political_stability_trend": {
      "value": "stable",
      "confidence": 0.65,
      "reasoning": "Italy political stability broadly maintained. European-wide stress from oil shock and market crash creates background pressure but institutions holding.",
      "last_updated": "2026-03-10T12:00:00Z",
      "source": "agent_10_trend_estimator",
      "run_id": "2026-W11"
    }
  },
  "metadata": {
    "active_flags": [
      {
        "factor": "macroeconomic.exchange_rate_vs_usd",
        "reason": "Large % change: 27.9% (threshold: 15%)",
        "previous_value": 1.1818,
        "new_value": 0.8518,
        "flagged_at": "2026-03-02T12:05:00Z",
        "run_id": "2026-W10"
      }
    ],
    "update_count": 103,
    "first_loaded": "2026-03-02T00:00:00Z",
    "data_quality": "HIGH"
  },
  "narrative": {
    "ai_generated": true,
    "generated_at": "2026-03-10T06:00:00Z",
    "run_id": "2026-W11",
    "executive_summary": "G7 finance ministers signal coordinated SPR release amid oil crisis. GDP growth at 0.7% (declining), inflation at 1.0% (rising). Investment risk score at 0.175, trending declining.",
    "key_changes_this_week": [
      "G7 finance ministers signal coordinated SPR release amid oil crisis",
      "Gdp Real Growth %: declining",
      "Inflation Cpi %: rising",
      "Overall Investment Risk Score: declining"
    ],
    "outlook": "GDP growth is on a downward trajectory. Inflation is rising, likely constraining monetary easing. Fiscal trajectory warrants monitoring as government debt is rising.",
    "investor_implications": "Low energy independence (0.200) makes the economy vulnerable to the oil price shock. Market accessibility score of 0.780 supports capital flows. Italy investment risk modestly elevated. European-wide energy and market stress weighing.",
    "data_quality_note": "Data quality is within acceptable parameters for this update cycle. All key indicators have adequate source coverage."
  },
  "code": "ITA",
  "name": "Italy",
  "executive_summary": "Italy faces moderate headwinds from the oil price surge with GDP at 0.6% and low energy independence. The Hormuz closure adds inflation pressure atop a fragile recovery. EU-Mercosur agreement provides trade diversification. Government debt at elevated levels constrains fiscal response to energy shock.",
  "key_changes": [
    "Hormuz closure drives oil price surge; Italy energy-dependent (Mar 1)",
    "EU-Mercosur Partnership Agreement signed -- positive for trade (Jan 17)",
    "GDP at 0.6% with fragile recovery amid external headwinds"
  ],
  "outlook": "Italy's recovery is the most vulnerable among major EU economies to an energy price shock. BTP-Bund spread may widen if growth falters. ECB rate cuts would support Italian sovereign debt dynamics. Structural reform momentum under Meloni provides positive backdrop if external shocks contained.",
  "investor_implications": "BTPs face spread widening risk if oil shock persists. Italian bank stocks sensitive to growth outlook and sovereign spread. Defense sector benefits from EU rearmament. Underweight Italian cyclicals exposed to energy costs.",
  "active_alerts": [],
  "layers": {
    "endowments": {
      "population": 58952704,
      "population_growth_pct": -0.053,
      "life_expectancy": 83.7,
      "population_total": 58952704,
      "hdi": 0.915,
      "median_age": 48.4
    },
    "institutions": {
      "political_stability": {},
      "under_international_sanctions": false,
      "democracy_index": 7.58,
      "regime_type": "flawed_democracy",
      "freedom_house_score": 89,
      "freedom_house_status": "free",
      "corruption_perception_index": 53,
      "press_freedom_index_rank": 49,
      "wgi_voice_accountability": 1.12,
      "wgi_political_stability": 0.58,
      "wgi_government_effectiveness": 0.61,
      "wgi_regulatory_quality": 0.64,
      "wgi_rule_of_law": 0.39,
      "wgi_control_of_corruption": 0.55,
      "head_of_state_name": "Sergio Mattarella",
      "head_of_state_title": "President",
      "head_of_government_name": "Giorgia Meloni",
      "next_national_election_date": "2027-10"
    },
    "economy": {
      "gdp_nominal_usd": 2380825077243.59,
      "gdp_real_growth_pct": 0.5,
      "gdp_per_capita_usd": 40385.3413957669,
      "inflation_cpi_pct": 1.7,
      "unemployment_rate_pct": 6.7,
      "current_account_pct_gdp": 1.08,
      "govt_debt_pct_gdp": 136.8,
      "fx_reserves_usd": 290547246726.359,
      "sovereign_credit_rating": "S&P: BBB+, Moody's: Baa2, Fitch: BBB",
      "central_bank_policy_rate_pct": 2.0,
      "total_exports_usd": 775983643285.188,
      "total_imports_usd": 721783449768.61,
      "gdp_growth_forecast_2026_pct": 0.8,
      "inflation_forecast_2026_pct": 2,
      "exchange_rate_vs_usd": 0.8552,
      "sovereign_bond_yield_10yr_pct": 3.51,
      "top_export_partners": [
        {
          "country": "DEU",
          "pct_of_total": 12.2
        },
        {
          "country": "FRA",
          "pct_of_total": 10.5
        },
        {
          "country": "USA",
          "pct_of_total": 10.3
        },
        {
          "country": "ESP",
          "pct_of_total": 5.2
        },
        {
          "country": "CHE",
          "pct_of_total": 4.8
        }
      ],
      "top_import_partners": [
        {
          "country": "DEU",
          "pct_of_total": 14.5
        },
        {
          "country": "FRA",
          "pct_of_total": 8.2
        },
        {
          "country": "CHN",
          "pct_of_total": 7.8
        },
        {
          "country": "NLD",
          "pct_of_total": 5.5
        },
        {
          "country": "ESP",
          "pct_of_total": 4.9
        }
      ],
      "avg_applied_tariff_pct": 5.0
    },
    "military": {
      "military_spending_usd": 32000000000,
      "military_expenditure_usd": 37400000000,
      "military_expenditure_pct_gdp": 1.6,
      "active_military_personnel": 165500,
      "alliance_memberships": [
        "NATO",
        "EU CSDP"
      ]
    },
    "relations": {},
    "derived": {
      "resource_self_sufficiency_index": 0.3,
      "energy_independence_index": 0.2,
      "supply_chain_chokepoint_exposure": 0.306,
      "composite_national_power_index": 54.8,
      "political_risk_premium_bps": 110,
      "market_accessibility_score": 0.78,
      "overall_investment_risk_score": 0.175
    }
  },
  "economy": {
    "top_export_partners": {
      "value": [
        {
          "country": "DEU",
          "pct_of_total": 12.2
        },
        {
          "country": "FRA",
          "pct_of_total": 10.5
        },
        {
          "country": "USA",
          "pct_of_total": 10.3
        },
        {
          "country": "ESP",
          "pct_of_total": 5.2
        },
        {
          "country": "CHE",
          "pct_of_total": 4.8
        }
      ],
      "confidence": 0.78,
      "last_updated": "2026-03-02T12:05:00Z",
      "source": "agent_pipeline",
      "run_id": "2026-W10"
    },
    "top_import_partners": {
      "value": [
        {
          "country": "DEU",
          "pct_of_total": 14.5
        },
        {
          "country": "FRA",
          "pct_of_total": 8.2
        },
        {
          "country": "CHN",
          "pct_of_total": 7.8
        },
        {
          "country": "NLD",
          "pct_of_total": 5.5
        },
        {
          "country": "ESP",
          "pct_of_total": 4.9
        }
      ],
      "confidence": 0.78,
      "last_updated": "2026-03-02T12:05:00Z",
      "source": "agent_pipeline",
      "run_id": "2026-W10"
    },
    "avg_applied_tariff_pct": {
      "value": 5.0,
      "confidence": 0.85,
      "last_updated": "2026-03-02T12:05:00Z",
      "source": "agent_pipeline",
      "run_id": "2026-W10"
    },
    "electricity_access_pct": {
      "value": 100,
      "confidence": 0.95,
      "last_updated": "2026-03-10T00:00:00Z",
      "source": "agent_pipeline",
      "run_id": "2026-W11"
    },
    "internet_users_pct": {
      "value": 89.2207,
      "confidence": 0.95,
      "last_updated": "2026-03-10T00:00:00Z",
      "source": "agent_pipeline",
      "run_id": "2026-W11"
    },
    "trade_openness_pct": 62.82
  },
  "institutions": {
    "under_international_sanctions": {
      "value": false,
      "confidence": 0.99,
      "last_updated": "2026-03-02T12:05:00Z",
      "source": "agent_pipeline",
      "run_id": "2026-W10"
    },
    "democracy_index": {
      "value": 7.58,
      "confidence": 0.95,
      "last_updated": "2026-03-02T12:05:00Z",
      "source": "agent_pipeline",
      "run_id": "2026-W10"
    },
    "regime_type": {
      "value": "flawed_democracy",
      "confidence": 0.95,
      "last_updated": "2026-03-02T12:05:00Z",
      "source": "agent_pipeline",
      "run_id": "2026-W10"
    },
    "freedom_house_score": {
      "value": 89,
      "confidence": 0.95,
      "last_updated": "2026-03-02T12:05:00Z",
      "source": "agent_pipeline",
      "run_id": "2026-W10"
    },
    "freedom_house_status": {
      "value": "free",
      "confidence": 0.95,
      "last_updated": "2026-03-02T12:05:00Z",
      "source": "agent_pipeline",
      "run_id": "2026-W10"
    },
    "corruption_perception_index": {
      "value": 53,
      "confidence": 0.93,
      "last_updated": "2026-03-02T12:05:00Z",
      "source": "agent_pipeline",
      "run_id": "2026-W10"
    },
    "press_freedom_index_rank": {
      "value": 49,
      "confidence": 0.95,
      "last_updated": "2026-03-02T12:05:00Z",
      "source": "agent_pipeline",
      "run_id": "2026-W10"
    },
    "wgi_voice_accountability": {
      "value": 1.115531,
      "confidence": 0.95,
      "last_updated": "2026-03-10T00:00:00Z",
      "source": "agent_pipeline",
      "run_id": "2026-W11"
    },
    "wgi_political_stability": {
      "value": 0.583321,
      "confidence": 0.95,
      "last_updated": "2026-03-10T00:00:00Z",
      "source": "agent_pipeline",
      "run_id": "2026-W11"
    },
    "wgi_government_effectiveness": {
      "value": 0.611037,
      "confidence": 0.95,
      "last_updated": "2026-03-10T00:00:00Z",
      "source": "agent_pipeline",
      "run_id": "2026-W11"
    },
    "wgi_regulatory_quality": {
      "value": 0.644032,
      "confidence": 0.95,
      "last_updated": "2026-03-10T00:00:00Z",
      "source": "agent_pipeline",
      "run_id": "2026-W11"
    },
    "wgi_rule_of_law": {
      "value": 0.390359,
      "confidence": 0.95,
      "last_updated": "2026-03-10T00:00:00Z",
      "source": "agent_pipeline",
      "run_id": "2026-W11"
    },
    "wgi_control_of_corruption": {
      "value": 0.550129,
      "confidence": 0.95,
      "last_updated": "2026-03-10T00:00:00Z",
      "source": "agent_pipeline",
      "run_id": "2026-W11"
    },
    "head_of_state_name": {
      "value": "Sergio Mattarella",
      "confidence": 0.92,
      "last_updated": "2026-03-02T12:05:00Z",
      "source": "agent_pipeline",
      "run_id": "2026-W10"
    },
    "head_of_state_title": {
      "value": "President",
      "confidence": 0.95,
      "last_updated": "2026-03-02T12:05:00Z",
      "source": "agent_pipeline",
      "run_id": "2026-W10"
    },
    "head_of_government_name": {
      "value": "Giorgia Meloni",
      "confidence": 0.9,
      "last_updated": "2026-03-02T12:05:00Z",
      "source": "agent_pipeline",
      "run_id": "2026-W10"
    },
    "next_national_election_date": {
      "value": "2027-10",
      "confidence": 0.8,
      "last_updated": "2026-03-02T12:05:00Z",
      "source": "agent_pipeline",
      "run_id": "2026-W10"
    }
  }
}